Workbook

Sheet 見積
B2: きみこい 本番見積（MOC検証後 MIN/MAX予算）
B3: 概算費用 MIN（税抜） | D3: =I31 -> 6830000 | E3: 円 | F3: 見積工数MIN × 8時間 × 概算時間単価
B4: 概算費用 MAX（税抜） | D4: =J31 -> 8099000 | E4: 円 | F4: 見積工数MAX × 8時間 × 概算時間単価
B5: 集計対象 | D5: 本番工数（MOC検証後） | F5: 中間リリース追加目安は未含有
B6: MOC検証後 MIN | D6: =E31 -> 155 | E6: 人日 | F6: 新列Mの合計
B7: MOC検証後 MAX | D7: =F31 -> 183.8 | E7: 人日 | F7: 新列Nの合計
B8: バッファ係数 | D8: 1.2 | E8: 倍 | F8: 本番工数（MOC検証後）の前提
B9: 見積工数 MIN | D9: =G31 -> 186 | E9: 人日 | F9: MOC検証後MIN × バッファ
B10: 見積工数 MAX | D10: =H31 -> 220.56 | E10: 人日 | F10: MOC検証後MAX × バッファ
B11: 1人日あたり時間 | D11: 8 | E11: 時間 | F11: 標準稼働時間
B12: 概算時間単価 | D12: 4590 | E12: 円/時間 | F12: 元見積660万円と179.75人日から算出
B15: No. | C15: 大項目 | D15: タスク数 | E15: MOC MIN | F15: MOC MAX | G15: 見積MIN人日 | H15: 見積MAX人日 | I15: MIN金額 | J15: MAX金額 | K15: 主な範囲
B16: 1 | C16: 00. 開発環境 | D16: 17 | E16: 4.7 | F16: 5.6 | G16: =ROUND(E16*$D$8,2) -> 5.64 | H16: =ROUND(F16*$D$8,2) -> 6.72 | I16: =ROUND(G16*$D$11*$D$12,-3) -> 207000 | J16: =ROUND(H16*$D$11*$D$12,-3) -> 247000 | K16: プロジェクト初期化 / バージョン管理 / フォルダ構成 / アセット導入 / 共通基盤
B17: 2 | C17: 01. 基盤システム | D17: 19 | E17: 4.6 | F17: 5 | G17: =ROUND(E17*$D$8,2) -> 5.52 | H17: =ROUND(F17*$D$8,2) -> 6 | I17: =ROUND(G17*$D$11*$D$12,-3) -> 203000 | J17: =ROUND(H17*$D$11*$D$12,-3) -> 220000 | K17: 入力定義 / 入力実装 / 仮想カーソル / サウンド基盤
B18: 3 | C18: 02. 疑似OS | D18: 17 | E18: 13.6 | F18: 16.2 | G18: =ROUND(E18*$D$8,2) -> 16.32 | H18: =ROUND(F18*$D$8,2) -> 19.44 | I18: =ROUND(G18*$D$11*$D$12,-3) -> 599000 | J18: =ROUND(H18*$D$11*$D$12,-3) -> 714000 | K18: ウィンドウ基盤 / ドラッグ操作 / フォーカス管理 / リサイズ操作 / デスクトップ ほか
B19: 4 | C19: 03. ADVエンジン | D19: 47 | E19: 28.8 | F19: 33.4 | G19: =ROUND(E19*$D$8,2) -> 34.56 | H19: =ROUND(F19*$D$8,2) -> 40.08 | I19: =ROUND(G19*$D$11*$D$12,-3) -> 1269000 | J19: =ROUND(H19*$D$11*$D$12,-3) -> 1472000 | K19: データ解析 / テキスト表示 / コマンド処理 / 全体進行制御 / 立ち絵制御 ほか
B20: 5 | C20: 04. アプリ実装 | D20: 34 | E20: 17.4 | F20: 20.4 | G20: =ROUND(E20*$D$8,2) -> 20.88 | H20: =ROUND(F20*$D$8,2) -> 24.48 | I20: =ROUND(G20*$D$11*$D$12,-3) -> 767000 | J20: =ROUND(H20*$D$11*$D$12,-3) -> 899000 | K20: LIMEチャット / LIME通話 / Googru検索 / メール機能 / 設定画面 ほか
B21: 6 | C21: 05. 進行・ループ | D21: 21 | E21: 13.4 | F21: 16.2 | G21: =ROUND(E21*$D$8,2) -> 16.08 | H21: =ROUND(F21*$D$8,2) -> 19.44 | I21: =ROUND(G21*$D$11*$D$12,-3) -> 590000 | J21: =ROUND(H21*$D$11*$D$12,-3) -> 714000 | K21: データ構造 / 進行管理（時間 / フラグ / 死に戻り / エンディング
B22: 7 | C22: 06. メタ演出 | D22: 17 | E22: 8.3 | F22: 9.6 | G22: =ROUND(E22*$D$8,2) -> 9.96 | H22: =ROUND(F22*$D$8,2) -> 11.52 | I22: =ROUND(G22*$D$11*$D$12,-3) -> 366000 | J22: =ROUND(H22*$D$11*$D$12,-3) -> 423000 | K22: グリッチ / マウスジャック / 偽装入力 / 疑似クラッシュ / 動画連携
B23: 8 | C23: 07. 仕上げ | D23: 13 | E23: 5.5 | F23: 6.5 | G23: =ROUND(E23*$D$8,2) -> 6.6 | H23: =ROUND(F23*$D$8,2) -> 7.8 | I23: =ROUND(G23*$D$11*$D$12,-3) -> 242000 | J23: =ROUND(H23*$D$11*$D$12,-3) -> 286000 | K23: Steam対応 / デバッグ機能 / ビルド設定
B24: 9 | C24: 妹 表情差分/Spine | D24: 11 | E24: 7.4 | F24: 8.8 | G24: =ROUND(E24*$D$8,2) -> 8.88 | H24: =ROUND(F24*$D$8,2) -> 10.56 | I24: =ROUND(G24*$D$11*$D$12,-3) -> 326000 | J24: =ROUND(H24*$D$11*$D$12,-3) -> 388000 | K24: 妹 表情差分/Spine
B25: 10 | C25: タッチアクション | D25: 12 | E25: 8.2 | F25: 9.7 | G25: =ROUND(E25*$D$8,2) -> 9.84 | H25: =ROUND(F25*$D$8,2) -> 11.64 | I25: =ROUND(G25*$D$11*$D$12,-3) -> 361000 | J25: =ROUND(H25*$D$11*$D$12,-3) -> 427000 | K25: タッチアクション
B26: 11 | C26: 技術剪定/演出検証 | D26: 8 | E26: 3.5 | F26: 3.8 | G26: =ROUND(E26*$D$8,2) -> 4.2 | H26: =ROUND(F26*$D$8,2) -> 4.56 | I26: =ROUND(G26*$D$11*$D$12,-3) -> 154000 | J26: =ROUND(H26*$D$11*$D$12,-3) -> 167000 | K26: 技術剪定/演出検証
B27: 12 | C27: Exeシナリオ読込/デバッグ | D27: 17 | E27: 8.1 | F27: 9.9 | G27: =ROUND(E27*$D$8,2) -> 9.72 | H27: =ROUND(F27*$D$8,2) -> 11.88 | I27: =ROUND(G27*$D$11*$D$12,-3) -> 357000 | J27: =ROUND(H27*$D$11*$D$12,-3) -> 436000 | K27: Exeシナリオ読込/デバッグ
... B30: 15 | C30: 09. QA/検証（MOC検証後・概算） | D30: 8 | E30: 8 | F30: 10 | G30: =ROUND(E30*$D$8,2) -> 9.6 | H30: =ROUND(F30*$D$8,2) -> 12 | I30: =ROUND(G30*$D$11*$D$12,-3) -> 353000 | J30: =ROUND(H30*$D$11*$D$12,-3) -> 441000 | K30: QA/検証
C31: 合計 | D31: =SUM(D16:D30) -> 264 | E31: =SUM(E16:E30) -> 155 | F31: =SUM(F16:F30) -> 183.8 | G31: =SUM(G16:G30) -> 186 | H31: =SUM(H16:H30) -> 220.56 | I31: =SUM(I16:I30) -> 6830000 | J31: =SUM(J16:J30) -> 8099000

Sheet MOC後詳細
A1: No. | B1: 大項目 | C1: 中項目 | D1: タスク | E1: MOC MIN | F1: MOC MAX | G1: 見積MIN人日 | H1: 見積MAX人日 | I1: 判断理由
A2: 1 | B2: 00. 開発環境 | C2: プロジェクト初期化 | D2: プロジェクト初期化 | E2: 0.1 | F2: 0.1 | G2: =ROUND(E2*見積!$D$8,2) -> 0.12 | H2: =ROUND(F2*見積!$D$8,2) -> 0.12 | I2: MOCで初期設定・導入が進んだため、本番では確認と整理中心
A3: 2 | B3: 00. 開発環境 | C3: プロジェクト初期化 | D3: メンバーサポート | E3: 0.6 | F3: 0.8 | G3: =ROUND(E3*見積!$D$8,2) -> 0.72 | H3: =ROUND(F3*見積!$D$8,2) -> 0.96 | I3: MOCで初期設定・導入が進んだため、本番では確認と整理中心
A4: 3 | B4: 00. 開発環境 | C4: バージョン管理 | D4: プロジェクトルートで git init 実行 | E4: 0.1 | F4: 0.1 | G4: =ROUND(E4*見積!$D$8,2) -> 0.12 | H4: =ROUND(F4*見積!$D$8,2) -> 0.12 | I4: MOCで初期設定・導入が進んだため、本番では確認と整理中心
A5: 4 | B5: 00. 開発環境 | C5: バージョン管理 | D5: .gitignore 作成 | E5: 0.1 | F5: 0.1 | G5: =ROUND(E5*見積!$D$8,2) -> 0.12 | H5: =ROUND(F5*見積!$D$8,2) -> 0.12 | I5: MOCで初期設定・導入が進んだため、本番では確認と整理中心
A6: 5 | B6: 00. 開発環境 | C6: バージョン管理 | D6: Git LFS初期化 | E6: 0.1 | F6: 0.1 | G6: =ROUND(E6*見積!$D$8,2) -> 0.12 | H6: =ROUND(F6*見積!$D$8,2) -> 0.12 | I6: MOCで初期設定・導入が進んだため、本番では確認と整理中心
A7: 6 | B7: 00. 開発環境 | C7: バージョン管理 | D7: メンバーサポート | E7: 0.6 | F7: 0.8 | G7: =ROUND(E7*見積!$D$8,2) -> 0.72 | H7: =ROUND(F7*見積!$D$8,2) -> 0.96 | I7: MOCで初期設定・導入が進んだため、本番では確認と整理中心
A8: 7 | B8: 00. 開発環境 | C8: フォルダ構成 | D8: Assets以下のフォルダ構成考案 | E8: 0.2 | F8: 0.2 | G8: =ROUND(E8*見積!$D$8,2) -> 0.24 | H8: =ROUND(F8*見積!$D$8,2) -> 0.24 | I8: MOCで初期設定・導入が進んだため、本番では確認と整理中心
A9: 8 | B9: 00. 開発環境 | C9: アセット導入 | D9: TextMeshPro 導入 | E9: 0.1 | F9: 0.1 | G9: =ROUND(E9*見積!$D$8,2) -> 0.12 | H9: =ROUND(F9*見積!$D$8,2) -> 0.12 | I9: MOCで初期設定・導入が進んだため、本番では確認と整理中心
A10: 9 | B10: 00. 開発環境 | C10: アセット導入 | D10: 日本語フォント(SDF)作成 | E10: 0.1 | F10: 0.1 | G10: =ROUND(E10*見積!$D$8,2) -> 0.12 | H10: =ROUND(F10*見積!$D$8,2) -> 0.12 | I10: MOCで初期設定・導入が進んだため、本番では確認と整理中心
A11: 10 | B11: 00. 開発環境 | C11: アセット導入 | D11: Input System 導入 | E11: 0.1 | F11: 0.1 | G11: =ROUND(E11*見積!$D$8,2) -> 0.12 | H11: =ROUND(F11*見積!$D$8,2) -> 0.12 | I11: MOCで初期設定・導入が進んだため、本番では確認と整理中心
A12: 11 | B12: 00. 開発環境 | C12: アセット導入 | D12: Spine Runtime 導入 | E12: 0.1 | F12: 0.1 | G12: =ROUND(E12*見積!$D$8,2) -> 0.12 | H12: =ROUND(F12*見積!$D$8,2) -> 0.12 | I12: Spine/表情差分/タッチ判定の本番品質化で増加
A13: 12 | B13: 00. 開発環境 | C13: アセット導入 | D13: Newtonsoft.Json 導入 | E13: 0.2 | F13: 0.2 | G13: =ROUND(E13*見積!$D$8,2) -> 0.24 | H13: =ROUND(F13*見積!$D$8,2) -> 0.24 | I13: MOCで初期設定・導入が進んだため、本番では確認と整理中心
... A265: 264 | B265: 09. QA/検証（MOC検証後・概算） | C265: QA/検証 | D265: 修正確認/再発チェック | E265: 1.1 | F265: 1.4 | G265: =ROUND(E265*見積!$D$8,2) -> 1.32 | H265: =ROUND(F265*見積!$D$8,2) -> 1.68 | I265: FB修正後の再確認を最低限残す
